{
  "schemaVersion": 1,
  "recordId": "fixture-acde/2026.05.23-900113",
  "title": "PM Lean Fixture Live Cycle 113: EIP-7702 wallet impact",
  "summary": "{ \"schemaVersion\": 1, \"source\": \"fixture-live\", \"fixtureLive\": true, \"cycle\": 113, \"topic\": \"EIP-7702 wallet impact\", \"eip\": \"EIP-7702\", \"summary\": \"Wallet and account-abstraction teams should review delegation safety te...",
  "decisions": [
    "Imported PM TLDR carries decision/action extraction where available."
  ],
  "provenance": {
    "generatedAt": "2026-06-01T14:21:14.426Z",
    "generator": "pm-lean/derive-summary",
    "generatorVersion": "0.1.0",
    "inputArtifactHashes": [
      "070f7156e3606da6fded731efbb7f8b35ef4ea4b1f3d6a4523263e1086deaabb",
      "3bf1736d05b17c92d56169655b034568123848d182bed5aff57aab769aafa821",
      "41df3195b2dc40f35cdc903d0aae1b9e674160a796421472bdb2559c64516222",
      "8684a5b7df6287f998b968b986a2061fc3c3fcf9f2e9102815780dcbd3c7a385"
    ],
    "provider": "fixture",
    "model": "deterministic-extractive"
  }
}
