{
  "schemaVersion": 1,
  "recordId": "fixture-acde/2026.05.22-900063",
  "title": "PM Lean Fixture Live Cycle 63: SFI movement watch",
  "summary": "{ \"schemaVersion\": 1, \"source\": \"fixture-live\", \"fixtureLive\": true, \"cycle\": 63, \"topic\": \"SFI movement watch\", \"eip\": \"EIP-8253\", \"summary\": \"Fork planners should compare replacement scope against existing Glamsterdam ...",
  "decisions": [
    "Imported PM TLDR carries decision/action extraction where available."
  ],
  "provenance": {
    "generatedAt": "2026-06-01T14:21:14.426Z",
    "generator": "pm-lean/derive-summary",
    "generatorVersion": "0.1.0",
    "inputArtifactHashes": [
      "37b7c24c5f2b29f305897b773f54e243e7a1899084d9d4cf69fd57f0f65c1b35",
      "509fa98b1deff68f77da73013b9a56b3ea7bd606dc7a188b546b1b100e73f36b",
      "5a1da5ddb71c877982a0f30bda59c3c9edf24ec892457d02bbee79324305f28d",
      "e7a74e64c3815fe71b966128e009e203189be093a9594a12014c52f0d5001b5a"
    ],
    "provider": "fixture",
    "model": "deterministic-extractive"
  }
}
