{
  "schemaVersion": 1,
  "recordId": "fixture-acde/2026.05.21-900002",
  "title": "PM Lean Fixture Live Cycle 2: EIP-7702 wallet impact",
  "summary": "{ \"schemaVersion\": 1, \"source\": \"fixture-live\", \"fixtureLive\": true, \"cycle\": 2, \"topic\": \"EIP-7702 wallet impact\", \"eip\": \"EIP-7702\", \"summary\": \"Wallet and account-abstraction teams should review delegation safety text...",
  "decisions": [
    "Imported PM TLDR carries decision/action extraction where available."
  ],
  "provenance": {
    "generatedAt": "2026-06-01T14:21:14.426Z",
    "generator": "pm-lean/derive-summary",
    "generatorVersion": "0.1.0",
    "inputArtifactHashes": [
      "0a0abbbda44eceee48bb9211c4f2275e022e1b16257da327ca485e28c43c5292",
      "1d4f141e56af82ffb9c23e87aafb8fdc422a7d147619c6b988a02d235ca6b498",
      "7761c15307561302e7daf33fc3117130f9214e4112e275a19a67f37c71704785",
      "f954414ff1bab2455b2085667f2eb907a227aa38ba6a96b886228207abaf9f9c"
    ],
    "provider": "fixture",
    "model": "deterministic-extractive"
  }
}
