{
  "schemaVersion": 1,
  "recordId": "fixture-acde/2026.05.21-900033",
  "title": "PM Lean Fixture Live Cycle 33: SFI movement watch",
  "summary": "{ \"schemaVersion\": 1, \"source\": \"fixture-live\", \"fixtureLive\": true, \"cycle\": 33, \"topic\": \"SFI movement watch\", \"eip\": \"EIP-8253\", \"summary\": \"Fork planners should compare replacement scope against existing Glamsterdam ...",
  "decisions": [
    "Imported PM TLDR carries decision/action extraction where available."
  ],
  "provenance": {
    "generatedAt": "2026-06-01T14:21:14.426Z",
    "generator": "pm-lean/derive-summary",
    "generatorVersion": "0.1.0",
    "inputArtifactHashes": [
      "07afab4040941baa0f5d6e17d36b0b94c1d0961354caedb063d9024285dc3b10",
      "315ac406cef4f1aab5f297832b0713a89a6b171b25cdac31be278af2d9462eff",
      "90d39b9049d38f9904eb1fdb7013004d167a4099f333c424995ffa5ecc5bcbe3",
      "ad2861ebf60f1a214d1ad5ab088b2542ee6b9c8c2cebfbb0428aa51e57bda63c"
    ],
    "provider": "fixture",
    "model": "deterministic-extractive"
  }
}
